gitlab_schedule_badge/__init__.py
gitlab_schedule_badge/__main__.py
gitlab_schedule_badge/cache.py
gitlab_schedule_badge/check.py
gitlab_schedule_badge/config.py
gitlab_schedule_badge/defs.py
gitlab_schedule_badge/httpd.py
gitlab_schedule_badge/log.py
gitlab_schedule_badge/pipeline_schedule.py
gitlab_schedule_badge/query.py
gitlab_schedule_badge/rest.py
gitlab_schedule_badge/state.py
gitlab_schedule_badge/theme.py
gitlab_schedule_badge/util.py
gitlab_schedule_badge/win32.py
gitlab_schedule_badge/wsgi.py
gitlab_schedule_badge/static/jquery-3.7.1.min.js
gitlab_schedule_badge/static/normalize.css
gitlab_schedule_badge/static/script.js
gitlab_schedule_badge/static/style.css
gitlab_schedule_badge/templates/index.html
gitlab_schedule_badge-0.4.0.dist-info/entry_points.txt
gitlab_schedule_badge-0.4.0.dist-info/licenses/LICENSE
gitlab_schedule_badge-0.4.0.dist-info/WHEEL
gitlab_schedule_badge-0.4.0.dist-info/METADATA
gitlab_schedule_badge-0.4.0.dist-info/RECORD
