Metadata-Version: 2.4
Name: gitlab-schedule-badge
Version: 0.4.0
Summary: Service to share GitLab scheduled job statuses with badges
Author-email: James Knight <git@jdknight.me>
Requires-Python: >=3.11
Classifier: Development Status :: 4 - Beta
Classifier: Environment :: Web Environment
Classifier: Intended Audience :: Developers
Classifier: License :: OSI Approved :: BSD License
Classifier: Operating System :: OS Independent
Classifier: Programming Language :: Python
Classifier: Programming Language :: Python :: 3 :: Only
Classifier: Programming Language :: Python :: 3
Classifier: Programming Language :: Python :: 3.11
Classifier: Programming Language :: Python :: 3.12
Classifier: Programming Language :: Python :: 3.13
License-File: LICENSE
Requires-Dist: flask
Requires-Dist: pybadges2
Requires-Dist: requests
Project-URL: Download, https://pypi.python.org/pypi/gitlab-schedule-badge
Project-URL: Source, https://gitlab.com/gitlab-schedule-badge/gitlab-schedule-badge
